ami_pipelines/__init__.py
ami_pipelines/py.typed
ami_pipelines/_jsii/__init__.py
ami_pipelines/_jsii/halloumi-ami-pipelines@0.0.40.jsii.tgz
halloumi_ami_pipelines-0.0.40.dist-info/LICENSE
halloumi_ami_pipelines-0.0.40.dist-info/METADATA
halloumi_ami_pipelines-0.0.40.dist-info/WHEEL
halloumi_ami_pipelines-0.0.40.dist-info/top_level.txt
halloumi_ami_pipelines-0.0.40.dist-info/RECORD
